array_adhoc/__init__.py
array_adhoc/cupy.py
array_adhoc/numpy.py
array_adhoc/torch.py
array_adhoc-0.0.1.dist-info/LICENSE
array_adhoc-0.0.1.dist-info/METADATA
array_adhoc-0.0.1.dist-info/WHEEL
array_adhoc-0.0.1.dist-info/top_level.txt
array_adhoc-0.0.1.dist-info/RECORD
