Metadata-Version: 2.1
Name: array-adhoc
Version: 0.0.1
Summary: Implements parts of the Python Array API
License: MIT License
Classifier: Programming Language :: Python :: 3
License-File: LICENSE
Provides-Extra: torch
Requires-Dist: torch ; extra == 'torch'
